{
    "name": "Speed",
    "icon": "power:textures/mob_effect/speed_master.png",
    "category": "power:stones",
    "sortnum": 34,
    "pages": [
        {
            "type": "patchouli:text",
            "text": [
                "$(l)Abilities$()",
                "$(li)",
                "Dash - teleports the player to the nearest entity, dealing damage to it.",
                "$(li)",
                "Acceleration - speeds up the player for a certain amount of time.",
                "$(li)",
                "Deceleration - slows down entities within an 8 block radius."
            ]
        },
        {
            "type": "patchouli:spotlight",
            "item": "power:speed_stone",
            "text": [
                "$(l)Passive Skills$()",
                "$(li)",
                "$(o)Condition:$() Player is sprinting.",
                "$(li)",
                "Blitz Attack: +25% damage.",
                "$(li)",
                "Supersonic Speed: 15% chance to gain \"Dash\" for 3 sec on attack."
            ]
        }
    ]
}